pcloud_dl/__init__.py
pcloud_dl/__main__.py
pcloud_dl/cli.py
pcloud_dl/downloader.py
pcloud_dl-0.1.8.dist-info/LICENSE
pcloud_dl-0.1.8.dist-info/METADATA
pcloud_dl-0.1.8.dist-info/WHEEL
pcloud_dl-0.1.8.dist-info/entry_points.txt
pcloud_dl-0.1.8.dist-info/top_level.txt
pcloud_dl-0.1.8.dist-info/RECORD
