Metadata-Version: 2.1
Name: pcloud-dl
Version: 0.1.8
Summary: pcloud downloader
Home-page: https://github.com/JavSensei/pcloud-dl
Author: JavierSC
Classifier: Programming Language :: Python :: 3
Classifier: License :: OSI Approved :: MIT License
Classifier: Operating System :: OS Independent
Classifier: Topic :: Utilities
Requires-Python: >=3.6
License-File: LICENSE
Requires-Dist: requests
Requires-Dist: tqdm
